beauty_ocean/__init__.py
beauty_ocean/cli.py
beauty_ocean/core/__init__.py
beauty_ocean/core/api.py
beauty_ocean/core/config.py
beauty_ocean/core/helpers.py
beauty_ocean/core/questions.py
beauty_ocean/droplet/__init__.py
beauty_ocean/droplet/api.py
beauty_ocean/droplet/choices.py
beauty_ocean/droplet/entry.py
beauty_ocean/droplet/helpers.py
beauty_ocean/droplet/questions.py
beauty_ocean-0.2.1.dist-info/METADATA
beauty_ocean-0.2.1.dist-info/RECORD
beauty_ocean-0.2.1.dist-info/WHEEL
beauty_ocean-0.2.1.dist-info/entry_points.txt
beauty_ocean-0.2.1.dist-info/top_level.txt
