Metadata-Version: 2.1
Name: beauty-ocean
Version: 0.2.1
Summary: Exploit DigitalOcean API through the console.
Home-page: https://github.com/manikos/beauty-ocean
Author: Nick Mavrakis
Author-email: mavrakis.n@gmail.com
License: MIT license
Project-URL: Documentation, https://beauty-ocean.readthedocs.io/en/latest/
Project-URL: Tracker, https://github.com/manikos/beauty-ocean/issues/
Keywords: cli digital-ocean DigitalOcean droplet inquirer
Platform: UNKNOWN
Classifier: Development Status :: 5 - Production/Stable
Classifier: Intended Audience :: Developers
Classifier: Environment :: Console
Classifier: Topic :: Software Development :: Build Tools
Classifier: License :: OSI Approved :: MIT License
Classifier: Natural Language :: English
Classifier: Programming Language :: Python :: 3
Classifier: Programming Language :: Python :: 3 :: Only
Classifier: Programming Language :: Python :: 3.6
Classifier: Programming Language :: Python :: 3.7
Requires-Python: >=3.6
Provides-Extra: test
Requires-Dist: Click (>=6.0)
Requires-Dist: python-digitalocean (>=1.13)
Requires-Dist: colored (>=1.3)
Requires-Dist: yaspin (>=0.14)
Requires-Dist: sshpubkeys (>=3.1)
Requires-Dist: inquirer (>=2.4)
Provides-Extra: test
Requires-Dist: pytest (>=3.8); extra == 'test'
Requires-Dist: coverage (>=4.5); extra == 'test'
Requires-Dist: pytest-cov (>=2.6); extra == 'test'
Requires-Dist: tox (>=3.3); extra == 'test'
Requires-Dist: codecov (>=2.0); extra == 'test'
